LICENSE.txt
MANIFEST.in
README.txt
setup.py
atoms/__init__.py
atoms/atoms.py
atoms.egg-info/PKG-INFO
atoms.egg-info/SOURCES.txt
atoms.egg-info/dependency_links.txt
atoms.egg-info/top_level.txt
atoms/tests/__init__.py
atoms/tests/atoms_tests.py
atoms/tests/data/1L2Y.pdb