Metadata-Version: 1.0
Name: atoms
Version: 0.1
Summary: Atomic data
Home-page: www.dansindhikara.com
Author: Daniel J. Sindhikara
Author-email: sindhikara@gmail.com
License: LGPL
Platform: UNKNOWN
